LICENSE.rst
README.md
nestor_qt/__init__.py
nestor_qt/__main__.py
nestor_qt/app.py
nestor_qt/helper_objects.py
nestor_qt/meta_windows.py
nestor_qt/resources/__init__.py
nestor_qt/resources/dialog_wait.ui
nestor_qt/resources/dialogmenu_csvheadermapping.ui
nestor_qt/resources/dialogmenu_databaseconnect.ui
nestor_qt/resources/dialogmenu_databaserunqueries.ui
nestor_qt/resources/dialogmenu_newproject.ui
nestor_qt/resources/dialogmenu_openproject.ui
nestor_qt/resources/dialogmenu_researchwindow.ui
nestor_qt/resources/dialogmenu_settings.ui
nestor_qt/resources/dialogmenu_specialreplace.ui
nestor_qt/resources/dialogmenu_termsofuse.ui
nestor_qt/resources/nestor-qt.png
nestor_qt/resources/taggingUI.ui
nestor_qt/store_data/DatabaseSchema.yaml
nestor_qt/store_data/HistoricalCSV_GraphDatabase.md
nestor_qt/store_data/__init__.py
nestor_qt/store_data/csvHeader.yaml
nestor_qt/store_data/database.py
nestor_qt/store_data/helper.py
nestor_qt/store_data/integration.py
nestor_qt/store_data/objects/__init__.py
nestor_qt/store_data/objects/human.py
nestor_qt/store_data/objects/issue.py
nestor_qt/store_data/objects/kpi.py
nestor_qt/store_data/objects/machine.py
nestor_qt/store_data/objects/maintenanceworkorder.py
nestor_qt/store_data/objects/plot.py
nestor_qt/store_data/objects/tag.py
nestor_qt/taggingUI_app.py
nestor_qt-0.3.5.dist-info/LICENSE.rst
nestor_qt-0.3.5.dist-info/METADATA
nestor_qt-0.3.5.dist-info/WHEEL
nestor_qt-0.3.5.dist-info/entry_points.txt
nestor_qt-0.3.5.dist-info/RECORD
